core/__init__.py
core/digits/__init__.py
core/digits/mathematical_functions.py
core/text/__init__.py
core/text/convert.py
core/text/regexp.py
core/text/string_functions.py
core/text/substr.py
django_postgresql_func/__init__.py
django_postgresql_func/digits/__init__.py
django_postgresql_func/digits/mathematical_functions.py
django_postgresql_func/text/__init__.py
django_postgresql_func/text/convert.py
django_postgresql_func/text/mixins.py
django_postgresql_func/text/regexp.py
django_postgresql_func/text/string_functions.py
django_postgresql_func/text/substr.py
dpf_test/__init__.py
dpf_test/asgi.py
dpf_test/settings.py
dpf_test/urls.py
dpf_test/utils.py
dpf_test/wsgi.py
test/__init__.py
test/models.py
test/migrations/0001_initial.py
test/migrations/0002_auto_20200229_1239.py
test/migrations/0003_digittable.py
test/migrations/0004_emptyt1.py
test/migrations/0005_auto_20200311_1335.py
test/migrations/__init__.py
django_postgresql_func-0.0.6.dist-info/LICENSE
django_postgresql_func-0.0.6.dist-info/METADATA
django_postgresql_func-0.0.6.dist-info/WHEEL
django_postgresql_func-0.0.6.dist-info/top_level.txt
django_postgresql_func-0.0.6.dist-info/RECORD
