Metadata-Version: 2.1
Name: django-postgresql-func
Version: 0.0.6
Summary: PostgreSQL Functions and Operators for Django. Full support for classic Django SQL functions
Home-page: https://github.com/lampofearth/django-postgresql-func
Author: lampofearth
Author-email: lampofearth@gmail.com
License: UNKNOWN
Project-URL: Documentation, https://py-orm.com/chapter/django-postgresql-func
Project-URL: Source, https://github.com/lampofearth/django-postgresql-func/
Project-URL: Tracker, https://github.com/lampofearth/django-postgresql-func/issues/
Platform: UNKNOWN
Classifier: Programming Language :: Python :: 3
Classifier: Framework :: Django
Classifier: License :: OSI Approved :: GNU General Public License (GPL)
Classifier: Operating System :: OS Independent
Classifier: Natural Language :: English
Requires-Python: >=3.6
Requires-Dist: django (>=2.0.0)
